tspgrasp-0.1.1.dist-info/LICENSE
tspgrasp-0.1.1.dist-info/METADATA
tspgrasp-0.1.1.dist-info/RECORD
tspgrasp-0.1.1.dist-info/top_level.txt
tspgrasp-0.1.1.dist-info/WHEEL
tspgrasp/base.py
tspgrasp/grasp.py
tspgrasp/environ.py
tspgrasp/__init__.py
tspgrasp/dataloader.py
tspgrasp/solution.py
tspgrasp/cython/random.cpython-310-x86_64-linux-gnu.so
tspgrasp/cython/__init__.cpython-310-x86_64-linux-gnu.so
tspgrasp/cython/utils.cpython-310-x86_64-linux-gnu.so
tspgrasp/cython/local_search.cpython-310-x86_64-linux-gnu.so
tspgrasp/cython/__init__.py
tspgrasp/cython/constructive.cpython-310-x86_64-linux-gnu.so
tspgrasp/cython/node.cpython-310-x86_64-linux-gnu.so
tspgrasp/cython/tour.cpython-310-x86_64-linux-gnu.so
tspgrasp/cython/problem.cpython-310-x86_64-linux-gnu.so
tspgrasp/cython/simulated_annealing.cpython-310-x86_64-linux-gnu.so
tspgrasp/pypure/grasp.py
tspgrasp/pypure/constructive.py
tspgrasp/pypure/tour.py
tspgrasp/pypure/local_search.py
tspgrasp/pypure/__init__.py
tspgrasp/pypure/node.py
tspgrasp/pypure/problem.py
tspgrasp/pypure/simulated_annealing.py
