Metadata-Version: 2.1
Name: tspgrasp
Version: 0.1.1
Summary: GRASP for TSP
Home-page: https://github.com/bruscalia/tsp-grasp
Download-URL: https://github.com/bruscalia/tsp-grasp
Author: Bruno Scalia C. F. Leite
Author-email: bruscalia12@gmail.com
License: Apache License 2.0
Keywords: Traveling Salesman Problem,TSP,Greedy Randomized Adaptive Search Procedures,Heuristics,Metaheuristics,Meta-heuristics,Greedy Algorithms,Local Search,Variable Neighborhood Search,Simulated Annealing
License-File: LICENSE
Requires-Dist: numpy >=1.19
Requires-Dist: Cython
Provides-Extra: dev
Requires-Dist: pytest ; extra == 'dev'
Provides-Extra: plot
Requires-Dist: matplotlib ; extra == 'plot'
